setup.py
nmeaall/__init__.py
nmeaall.egg-info/PKG-INFO
nmeaall.egg-info/SOURCES.txt
nmeaall.egg-info/dependency_links.txt
nmeaall.egg-info/top_level.txt