Metadata-Version: 2.1
Name: nmeaall
Version: 1.2
Summary: Can access all nmea file types with formats GPGGA, GPRMC and GPGSA as well as GNSS and NAVIC data too
Author: VishalJain_NIOT
Author-email: vishaljain9516@gmail.com
